AUTHORS
LICENSE
MANIFEST.in
README.rst
setup.py
cmsplugin_fancybox/__init__.py
cmsplugin_fancybox/admin.py
cmsplugin_fancybox/cms_plugins.py
cmsplugin_fancybox/forms.py
cmsplugin_fancybox/models.py
cmsplugin_fancybox/migrations/0001_initial.py
cmsplugin_fancybox/migrations/0002_auto__add_field_fancyboxplugin_target_image_title.py
cmsplugin_fancybox/migrations/0003_auto__add_field_fancyboxplugin_link_image_alignment.py
cmsplugin_fancybox/migrations/__init__.py
cmsplugin_fancybox/static/cmsplugin_fancybox/fancybox/blank.gif
cmsplugin_fancybox/static/cmsplugin_fancybox/fancybox/fancybox_loading.gif
cmsplugin_fancybox/static/cmsplugin_fancybox/fancybox/fancybox_sprite.png
cmsplugin_fancybox/static/cmsplugin_fancybox/fancybox/jquery.easing-1.3.pack.js
cmsplugin_fancybox/static/cmsplugin_fancybox/fancybox/jquery.fancybox.css
cmsplugin_fancybox/static/cmsplugin_fancybox/fancybox/jquery.fancybox.js
cmsplugin_fancybox/static/cmsplugin_fancybox/fancybox/jquery.fancybox.pack.js
cmsplugin_fancybox/static/cmsplugin_fancybox/js/cmsplugin_fancybox.js
cmsplugin_fancybox/static/cmsplugin_fancybox/js/jquery.js
cmsplugin_fancybox/templates/cmsplugin_fancybox/.cmsplugin_fancybox_image.html.swp
cmsplugin_fancybox/templates/cmsplugin_fancybox/cmsplugin_fancybox_image.html
cmsplugin_fancybox/templates/cmsplugin_fancybox/cmsplugin_fancybox_richtext.html
django_cms_fancybox.egg-info/PKG-INFO
django_cms_fancybox.egg-info/SOURCES.txt
django_cms_fancybox.egg-info/dependency_links.txt
django_cms_fancybox.egg-info/not-zip-safe
django_cms_fancybox.egg-info/requires.txt
django_cms_fancybox.egg-info/top_level.txt